{
    "categories": [
        {
            "name": "Home",
            "api": "https://raw.githubusercontent.com/rakshay905/allwallpapers/main/files/bestwallpapers.json",
            "description": "Best wallpapers"
        },
        {
            "name": "3D",
            "api": "https://raw.githubusercontent.com/rakshay905/allwallpapers/main/files/3dwallpapers.json",
            "description": "3D wallpapers"
        },
        {
            "name": "Abstract Wallpapers",
            "api": "https://raw.githubusercontent.com/rakshay905/allwallpapers/main/files/abstractwallpapers.json",
            "description": "Abstract wallpapers"
        },
        {
            "name": "Alone",
            "api": "https://raw.githubusercontent.com/rakshay905/allwallpapers/main/files/alonewallpapers.json",
            "description": "Alone wallpapers"
        },
        {
            "name": "Animals & Birds",
            "api": "https://raw.githubusercontent.com/rakshay905/allwallpapers/main/files/animalsbirdswallpapers.json",
            "description": "Animals and Birds wallpapers"
        },
        {
            "name": "Anime",
            "api": "https://raw.githubusercontent.com/rakshay905/allwallpapers/main/files/animewallpapers.json",
            "description": "Anime wallpapers"
        },
        {
            "name": "Dark Wallpapers",
            "api": "https://raw.githubusercontent.com/rakshay905/allwallpapers/main/files/darkwallpapers.json",
            "description": "Dark wallpapers"
        },
        {
            "name": "flower Wallpapers",
            "api": "https://raw.githubusercontent.com/rakshay905/allwallpapers/main/files/flowerswallpapers.json",
            "description": "Flower wallpapers"
        }
    ]
}
